Metadata-Version: 2.4
Name: dvc
Version: 3.65.0
Summary: Git for data scientists - manage your code and data together
Author-email: Dmitry Petrov <dmitry@dvc.org>
Maintainer-email: Treeverse <support@dvc.org>
License-Expression: Apache-2.0
Project-URL: Documentation, https://dvc.org/doc
Project-URL: Issues, https://github.com/treeverse/dvc/issues
Project-URL: Source, https://github.com/treeverse/dvc
Keywords: ai,collaboration,data-science,data-version-control,developer-tools,git,machine-learning,reproducibility
Classifier: Development Status :: 4 - Beta
Classifier: Programming Language :: Python :: 3
Classifier: Programming Language :: Python :: 3.9
Classifier: Programming Language :: Python :: 3.10
Classifier: Programming Language :: Python :: 3.11
Classifier: Programming Language :: Python :: 3.12
Classifier: Programming Language :: Python :: 3.13
Classifier: Programming Language :: Python :: 3.14
Requires-Python: >=3.9
License-File: LICENSE
Requires-Dist: attrs>=22.2.0
Requires-Dist: celery
Requires-Dist: colorama>=0.3.9
Requires-Dist: configobj>=5.0.9
Requires-Dist: distro>=1.3
Requires-Dist: dpath<3,>=2.1.0
Requires-Dist: dulwich
Requires-Dist: dvc-data<3.18,>=3.17.0
Requires-Dist: dvc-http>=2.29.0
Requires-Dist: dvc-objects
Requires-Dist: dvc-render<2,>=1.0.1
Requires-Dist: dvc-studio-client<1,>=0.21
Requires-Dist: dvc-task<1,>=0.3.0
Requires-Dist: flatten_dict<1,>=0.4.1
Requires-Dist: flufl.lock<9,>=8.1.0
Requires-Dist: fsspec>=2024.2.0
Requires-Dist: funcy>=1.14
Requires-Dist: grandalf<1,>=0.7
Requires-Dist: gto<2,>=1.6.0
Requires-Dist: hydra-core>=1.1
Requires-Dist: iterative-telemetry>=0.0.7
Requires-Dist: kombu
Requires-Dist: networkx>=2.5
Requires-Dist: omegaconf
Requires-Dist: packaging>=19
Requires-Dist: pathspec>=0.10.3
Requires-Dist: platformdirs<5,>=3.1.1
Requires-Dist: psutil>=5.8
Requires-Dist: pydot>=1.2.4
Requires-Dist: pygtrie>=2.3.2
Requires-Dist: pyparsing>=2.4.7
Requires-Dist: requests>=2.22
Requires-Dist: rich>=12
Requires-Dist: ruamel.yaml>=0.17.11
Requires-Dist: scmrepo<4,>=3.5.2
Requires-Dist: shortuuid>=0.5
Requires-Dist: shtab<2,>=1.3.4
Requires-Dist: tabulate>=0.8.7
Requires-Dist: tomlkit>=0.11.1
Requires-Dist: tqdm<5,>=4.63.1
Requires-Dist: voluptuous>=0.11.7
Requires-Dist: zc.lockfile>=1.2.1
Provides-Extra: all
Requires-Dist: dvc[azure,gdrive,gs,hdfs,oss,s3,ssh,webdav,webhdfs]; extra == "all"
Provides-Extra: azure
Requires-Dist: dvc-azure<4,>=3.1.0; extra == "azure"
Provides-Extra: dev
Requires-Dist: dvc[azure,gdrive,gs,hdfs,lint,oss,s3,ssh,tests,webdav,webhdfs]; extra == "dev"
Provides-Extra: gdrive
Requires-Dist: dvc-gdrive<4,>=3; extra == "gdrive"
Provides-Extra: gs
Requires-Dist: dvc-gs<4,>=3.0.2; extra == "gs"
Provides-Extra: hdfs
Requires-Dist: dvc-hdfs<4,>=3; extra == "hdfs"
Provides-Extra: lint
Requires-Dist: mypy==1.19.1; extra == "lint"
Requires-Dist: pandas-stubs; extra == "lint"
Requires-Dist: types-colorama; extra == "lint"
Requires-Dist: types-psutil; extra == "lint"
Requires-Dist: types-pyinstaller; extra == "lint"
Requires-Dist: types-requests; extra == "lint"
Requires-Dist: types-tabulate; extra == "lint"
Requires-Dist: types-toml; extra == "lint"
Requires-Dist: types-tqdm; extra == "lint"
Requires-Dist: typing-extensions; extra == "lint"
Provides-Extra: oss
Requires-Dist: dvc-oss<4,>=3; extra == "oss"
Provides-Extra: s3
Requires-Dist: dvc-s3<4,>=3.2.1; extra == "s3"
Provides-Extra: ssh
Requires-Dist: dvc-ssh<5,>=4; extra == "ssh"
Provides-Extra: ssh-gssapi
Requires-Dist: dvc-ssh[gssapi]<5,>=4; extra == "ssh-gssapi"
Provides-Extra: testing
Requires-Dist: pytest-benchmark[histogram]<6,>=5; extra == "testing"
Requires-Dist: uv; extra == "testing"
Provides-Extra: tests
Requires-Dist: dvc[testing]; extra == "tests"
Requires-Dist: beautifulsoup4>=4.4; extra == "tests"
Requires-Dist: dvc-ssh; extra == "tests"
Requires-Dist: filelock; extra == "tests"
Requires-Dist: pytest<9,>=7; extra == "tests"
Requires-Dist: pytest-rerunfailures<17.0; extra == "tests"
Requires-Dist: pytest-cov>=4.1.0; extra == "tests"
Requires-Dist: pytest-docker<4,>=1; extra == "tests"
Requires-Dist: pytest-mock; extra == "tests"
Requires-Dist: pytest-test-utils; extra == "tests"
Requires-Dist: pytest-timeout>=2; extra == "tests"
Requires-Dist: pytest-xdist>=3.2; extra == "tests"
Requires-Dist: pywin32>=225; sys_platform == "win32" and extra == "tests"
Requires-Dist: tzdata; sys_platform == "win32" and extra == "tests"
Requires-Dist: sqlalchemy<3,>=1; extra == "tests"
Requires-Dist: pandas>=1; extra == "tests"
Provides-Extra: webdav
Requires-Dist: dvc-webdav<4,>=3.0.1; extra == "webdav"
Provides-Extra: webhdfs
Requires-Dist: dvc-webhdfs<4,>=3.1; extra == "webhdfs"
Provides-Extra: webhdfs-kerberos
Requires-Dist: dvc-webhdfs[kerberos]<4,>=3.1; extra == "webhdfs-kerberos"
Dynamic: license-file
